pyrp/__init__.py
pyrp/rp.py
pyrp_slequar-0.0.2.dist-info/LICENSE
pyrp_slequar-0.0.2.dist-info/METADATA
pyrp_slequar-0.0.2.dist-info/WHEEL
pyrp_slequar-0.0.2.dist-info/top_level.txt
pyrp_slequar-0.0.2.dist-info/RECORD
