Metadata-Version: 2.1
Name: pyrp-slequar
Version: 0.0.2
Summary: A lightweight ranked pairs python package
Home-page: https://github.com/sjlequar/PyRP
Author: Simon Lequar
Author-email: simon.lequar@gmail.com
License: UNKNOWN
Platform: UNKNOWN
Classifier: Programming Language :: Python :: 3
Classifier: License :: OSI Approved :: MIT License
Classifier: Operating System :: OS Independent
Requires-Python: >=3.6
